izinscope/__init__.py
izinscope-0.4.1.dist-info/LICENSE
izinscope-0.4.1.dist-info/METADATA
izinscope-0.4.1.dist-info/WHEEL
izinscope-0.4.1.dist-info/entry_points.txt
izinscope-0.4.1.dist-info/RECORD
