Metadata-Version: 2.3
Name: izinscope
Version: 0.4.1
Summary: **izinscope** est un outil en ligne de commande permettant de vérifier si des adresses IP ou des domaines se trouvent dans un scope défini (IP, CIDR, domaines résolus). Il facilite l’identification des ressources “in-scope” et peut générer des rapports TXT ou CSV.
License: MIT
Author: Mahafaly Randriamiarisoa
Requires-Python: >=3.9
Classifier: License :: OSI Approved :: MIT License
Classifier: Programming Language :: Python :: 3
Classifier: Programming Language :: Python :: 3.9
Classifier: Programming Language :: Python :: 3.10
Classifier: Programming Language :: Python :: 3.11
Classifier: Programming Language :: Python :: 3.12
Classifier: Programming Language :: Python :: 3.13
Requires-Dist: dnspython (>=2.7.0,<3.0.0)
